dalood/__init__.py
dalood/data_wrapper.py
dalood/exception.py
dalood/manager.py
dalood/regex.py
dalood/version.py
dalood/loader/__init__.py
dalood/loader/base.py
dalood/loader/file.py
dalood/loader/json.py
dalood/loader/map.py
dalood/loader/memory.py
dalood/loader/pandas.py
dalood/loader/text.py
dalood/loader/url.py
dalood/loader/yaml.py
dalood-2025.1.dist-info/METADATA
dalood-2025.1.dist-info/WHEEL
dalood-2025.1.dist-info/licenses/LICENSE.txt
dalood-2025.1.dist-info/RECORD
