Metadata-Version: 2.4
Name: Dalood
Version: 2025.1
Summary: Extensible on-demand file loading with cache management.
Project-URL: Homepage, https://gitlab.inria.fr/jrye/dalood
Project-URL: Source, https://gitlab.inria.fr/jrye/dalood.git
Project-URL: Documentation, https://jrye.gitlabpages.inria.fr/dalood
Project-URL: Issues, https://gitlab.inria.fr/jrye/dalood/-/issues
Author-email: Jan-Michael Rye <jan-michael.rye@inria.fr>
License: MIT License
License-File: LICENSE.txt
Classifier: License :: OSI Approved :: MIT License
Classifier: Operating System :: OS Independent
Classifier: Programming Language :: Python :: 3
Requires-Python: >=3.6
Requires-Dist: pandas
Requires-Dist: pyyaml
Requires-Dist: requests
Requires-Dist: requests-file-adapter
Requires-Dist: sqlalchemy
Provides-Extra: test
Requires-Dist: coverage; extra == 'test'
